{
  "db_name": "PostgreSQL",
  "query": "\n        INSERT INTO gateway_description (\n            gateway_identity_key,\n            moniker,\n            website,\n            security_contact,\n            details,\n            last_updated_utc\n        ) VALUES ($1, $2, $3, $4, $5, $6)\n        ON CONFLICT (gateway_identity_key) DO UPDATE SET\n            moniker = excluded.moniker,\n            website = excluded.website,\n            security_contact = excluded.security_contact,\n            details = excluded.details,\n            last_updated_utc = excluded.last_updated_utc\n        ",
  "describe": {
    "columns": [],
    "parameters": {
      "Left": [
        "Varchar",
        "Varchar",
        "Varchar",
        "Varchar",
        "Varchar",
        "Int8"
      ]
    },
    "nullable": []
  },
  "hash": "de79ab87b392b9dd087820dfd2d72a8ee5522891233c7d26b8670ee84e641774"
}
