{
  "db_name": "SQLite",
  "query": "\n                SELECT serialised_signatures, serialization_revision as \"serialization_revision: u8\"\n                FROM global_expiration_date_signatures\n                WHERE expiration_date = ? AND epoch_id = ?\n            ",
  "describe": {
    "columns": [
      {
        "name": "serialised_signatures",
        "ordinal": 0,
        "type_info": "Blob"
      },
      {
        "name": "serialization_revision: u8",
        "ordinal": 1,
        "type_info": "Integer"
      }
    ],
    "parameters": {
      "Right": 2
    },
    "nullable": [
      false,
      false
    ]
  },
  "hash": "3cc446220668fb3e02f0578104291d2a2af57656b405212af414d765b2263347"
}
